matMulti/__init__.py
matMulti/product.py
product/__init__.py
product/product.py
matMulti-0.0.5.dist-info/LICENSE.txt
matMulti-0.0.5.dist-info/METADATA
matMulti-0.0.5.dist-info/WHEEL
matMulti-0.0.5.dist-info/top_level.txt
matMulti-0.0.5.dist-info/RECORD
