Metadata-Version: 2.1
Name: matMulti
Version: 0.0.5
Summary: A package to multiply two matrix of any dimensions
Home-page: https://github.com/SajalDasShovon/Own-Simple-Python-Package
Author: Sajal Das Shovon
Author-email: shovon030cse.kuet@gmail.com
License: MIT
Keywords: matrixMultiplier
Platform: UNKNOWN
Classifier: Development Status :: 5 - Production/Stable
Classifier: Intended Audience :: Education
Classifier: Operating System :: OS Independent
Classifier: License :: OSI Approved :: MIT License
Classifier: Programming Language :: Python :: 3
License-File: LICENSE.txt
